pymoldflow/__about__.py
pymoldflow/__init__.py
pymoldflow/base.py
pymoldflow/data_io.py
pymoldflow/runstudy.py
pymoldflow/studymod.py
pymoldflow/studyrlt.py
pymoldflow-0.0.3.dist-info/LICENSE
pymoldflow-0.0.3.dist-info/METADATA
pymoldflow-0.0.3.dist-info/WHEEL
pymoldflow-0.0.3.dist-info/top_level.txt
pymoldflow-0.0.3.dist-info/RECORD
