Metadata-Version: 2.1
Name: pymoldflow
Version: 0.0.3
Summary: Automation tools for Autodesk Moldflow
Home-page: https://github.com/tianyikillua/pymoldflow
Author: Tianyi Li
Author-email: tianyikillua@gmail.com
License: License :: OSI Approved :: MIT License
Platform: UNKNOWN
Classifier: License :: OSI Approved :: MIT License
Classifier: Development Status :: 4 - Beta
Classifier: Operating System :: Microsoft :: Windows
Classifier: Programming Language :: Python
Classifier: Programming Language :: Python :: 3.6
Classifier: Programming Language :: Python :: 3.7
Classifier: Intended Audience :: Science/Research
Classifier: Topic :: Scientific/Engineering
Classifier: Topic :: Scientific/Engineering :: Physics
Requires-Dist: numpy
Requires-Dist: meshio
Requires-Dist: lxml
Requires-Dist: pyyaml
